MANIFEST.in
README.md
ent.c
ent.pyx
setup.py
pyent.egg-info/PKG-INFO
pyent.egg-info/SOURCES.txt
pyent.egg-info/dependency_links.txt
pyent.egg-info/not-zip-safe
pyent.egg-info/top_level.txt