Metadata-Version: 2.1
Name: pyent
Version: 0.0.1
Summary: Unix utility `ent` reimplement with cython. Calculating data entropy
Home-page: https://github.com/inndy/pyent
Author: Inndy Lin
Author-email: inndy.tw@gmail.com
License: UNKNOWN
Platform: UNKNOWN
Classifier: Programming Language :: Python :: 3
Classifier: License :: OSI Approved :: MIT License
Requires-Python: >=3.6
